
  [
    { 
      "id":1,
      "title": "Tesla Model X", 
      "category": "SUV", 
      "type": "New", 
      "image": "https://i.postimg.cc/6QBpjPBd/stock-img4.jpg",
      "mileage":"50 Miles", 
      "fill": "Petrol", 
      "work": "Automatic", 
      "price": "$150,000"
    },
    {   "id":2,
       "title": "BMW 3 Series", 
      "category": "Sedan", 
      "type": "Used", 
      "image": "https://i.postimg.cc/0QfmXmgN/stock-img3.jpg",
      "mileage": "2 Miles",
      "fill": "Gasoline",
      "work": "Automatic",
      "price": "$120,000"
    },
    {
       "id":3,
      "title": "Ford Mustang GT",
      "category": "Coupe",
      "type": "New",
      "image": "https://i.postimg.cc/gJ01rVK9/stock-img1.jpg",
      "mileage": "20 Miles",
      "fill": "Gasoline",
      "work": "Manual",
      "price": "$55,000"
  },
  {
      "id":4,
      "title": "Toyota Camry",
      "category": "SUV",
      "type": "Used",
      "image": "https://i.postimg.cc/3xJqtjPk/stock-img2.jpg",
      "mileage": "25,000 Miles",
      "fill": "Hybrid",
      "work": "Automatic",
      "price": "$22,000"
  },
  {
      "id":5,
      "title": "BMW X5",
      "category": "SUV",
      "type": "In Stock",
      "image": "https://i.postimg.cc/6QBpjPBd/stock-img4.jpg",
      "mileage": "15 Miles",
      "fill": "Diesel",
      "work": "Automatic",
      "price": "$75,000"
  },
  {
      "id":6,
      "title": "Chevrolet Corvette",
      "category": "Coupe",
      "type": "In Stock",
      "image": "https://i.postimg.cc/gJ01rVK9/stock-img1.jpg",
      "mileage": "5 Miles",
      "fill": "Gasoline",
      "work": "Automatic",
      "price": "$80,000"
  },
  {
     "id":7,
      "title": "Honda Civic",
      "category": "HatchBack",
      "type": "Used",
      "image": "https://i.postimg.cc/6QBpjPBd/stock-img4.jpg",
      "mileage": "30,000 Miles",
      "fill": "Petrol",
      "work": "Automatic",
      "price": "$18,000"
  },
  {    "id":8,
      "title": "Mercedes-Benz G-Wagon",
      "category": "Hatchback",
      "type": "In Stock",
      "image": "https://i.postimg.cc/3xJqtjPk/stock-img2.jpg",
      "mileage": "10 Miles",
      "fill": "Diesel",
      "work": "Automatic",
      "price": "$130,000"
  },
  {   "id":9,
      "title": "Audi A6",
      "category": "Sedan",
      "type": "New",
      "image": "https://i.postimg.cc/gJ01rVK9/stock-img1.jpg",
      "mileage": "12 Miles",
      "fill": "Hybrid",
      "work": "Automatic",
      "price": "$60,000"
  },
  {   "id":10,
      "title": "Range Rover Sport",
      "category": "SUV",
      "type": "New",
      "image": "https://i.postimg.cc/3xJqtjPk/stock-img2.jpg",
      "mileage": "8 Miles",
      "fill": "Diesel",
      "work": "Automatic",
      "price": "$90,000"
  },
  {  "id":11,
    "title": "Range Rover Sport",
    "category": "Hybrid",
    "type": "New",
    "image": "https://i.postimg.cc/3xJqtjPk/stock-img2.jpg",
    "mileage": "8 Miles",
    "fill": "Diesel",
    "work": "Automatic",
    "price": "$90,000"
},
  {
    "id": 12,
    "title": "Tesla Model S",
    "category": "Sedan",
    "type": "New",
    "image": "https://i.postimg.cc/3xJqtjPk/stock-img2.jpg",
    "mileage": "0 Miles",
    "fill": "Electric",
    "work": "Automatic",
    "price": "$95,000"
  },
  {
    "id": 13,
    "title": "Tesla Model Y",
    "category": "SUV",
    "type": "In Stock",
    "image": "https://i.postimg.cc/gJ01rVK9/stock-img1.jpg",
    "mileage": "5 Miles",
    "fill": "Electric",
    "work": "Automatic",
    "price": "$58,000"
  },
  {
    "id": 14,
    "title": "Ford Mustang Mach-E",
    "category": "SUV",
    "type": "New",
    "image": "https://i.postimg.cc/0QfmXmgN/stock-img3.jpg",
    "mileage": "10 Miles",
    "fill": "Electric",
    "work": "Automatic",
    "price": "$65,000"
  },
  {
    "id": 15,
    "title": "Chevrolet Bolt EV",
    "category": "Hatchback",
    "type": "New",
    "image": "https://i.postimg.cc/6QBpjPBd/stock-img4.jpg",
    "mileage": "0 Miles",
    "fill": "Electric",
    "work": "Automatic",
    "price": "$32,000"
  },
  {
    "id": 16,
    "title": "Nissan Leaf",
    "category": "Hatchback",
    "type": "In Stock",
    "image": "https://i.postimg.cc/0QfmXmgN/stock-img3.jpg",
    "mileage": "8 Miles",
    "fill": "Electric",
    "work": "Automatic",
    "price": "$28,000"
  },
  {
    "id": 17,
    "title": "BMW iX",
    "category": "SUV",
    "type": "In Stock",
    "image": "https://i.postimg.cc/3xJqtjPk/stock-img2.jpg",
    "mileage": "2 Miles",
    "fill": "Electric",
    "work": "Automatic",
    "price": "$85,000"
  },
  {
    "id": 18,
    "title": "Hyundai Kona Electric",
    "category": "SUV",
    "type": "New",
    "image": "https://i.postimg.cc/6QBpjPBd/stock-img4.jpg",
    "mileage": "3 Miles",
    "fill": "Electric",
    "work": "Automatic",
    "price": "$39,000"
  },
  {
    "id": 19,
    "title": "Volkswagen ID.4",
    "category": "Hybrid",
    "type": "Used",
    "image": "https://i.postimg.cc/gJ01rVK9/stock-img1.jpg",
    "mileage": "4 Miles",
    "fill": "Electric",
    "work": "Automatic",
    "price": "$45,000"
  },
    {
      "id": 12,
      "title": "Tesla Model S",
      "category": "Sedan",
      "type": "New",
      "image": "https://i.postimg.cc/3xJqtjPk/stock-img2.jpg",
      "mileage": "0 Miles",
      "fill": "Electric",
      "work": "Automatic",
      "price": "$95,000"
    },
    {
      "id": 13,
      "title": "Tesla Model Y",
      "category": "Coupe",
      "type": "Used",
      "image": "https://i.postimg.cc/gJ01rVK9/stock-img1.jpg",
      "mileage": "5 Miles",
      "fill": "Electric",
      "work": "Automatic",
      "price": "$58,000"
    },
    {
      "id": 14,
      "title": "Ford Mustang Mach-E",
      "category": "HatchBack",
      "type": "New",
      "image": "https://i.postimg.cc/0QfmXmgN/stock-img3.jpg",
      "mileage": "10 Miles",
      "fill": "Electric",
      "work": "Automatic",
      "price": "$65,000"
    },
    {
      "id": 15,
      "title": "Chevrolet Bolt EV",
      "category": "Hatchback",
      "type": "New",
      "image": "https://i.postimg.cc/6QBpjPBd/stock-img4.jpg",
      "mileage": "0 Miles",
      "fill": "Electric",
      "work": "Automatic",
      "price": "$32,000"
    },
    {
      "id": 16,
      "title": "Nissan Leaf",
      "category": "Hatchback",
      "type": "In Stock",
      "image": "https://i.postimg.cc/0QfmXmgN/stock-img3.jpg",
      "mileage": "8 Miles",
      "fill": "Electric",
      "work": "Automatic",
      "price": "$28,000"
    },
    {
      "id": 17,
      "title": "BMW iX",
      "category": "Sedan",
      "type": "In Stock",
      "image": "https://i.postimg.cc/3xJqtjPk/stock-img2.jpg",
      "mileage": "2 Miles",
      "fill": "Electric",
      "work": "Automatic",
      "price": "$85,000"
    },
    {
      "id": 18,
      "title": "Hyundai Kona Electric",
      "category": "Hybrid",
      "type": "In Stock",
      "image": "https://i.postimg.cc/6QBpjPBd/stock-img4.jpg",
      "mileage": "3 Miles",
      "fill": "Electric",
      "work": "Automatic",
      "price": "$39,000"
    },
    {
      "id": 19,
      "title": "Volkswagen ID.4",
      "category": "HatchBack",
      "type": "In Stock",
      "image": "https://i.postimg.cc/gJ01rVK9/stock-img1.jpg",
      "mileage": "4 Miles",
      "fill": "Electric",
      "work": "Automatic",
      "price": "$45,000"
    }
  
]